pycine/__init__.py
pycine/cine.py
pycine/file.py
pycine/linLUT.py
pycine/raw.py
pycine_lite-0.4.0.dist-info/licenses/LICENSE
pycine_lite-0.4.0.dist-info/METADATA
pycine_lite-0.4.0.dist-info/WHEEL
pycine_lite-0.4.0.dist-info/top_level.txt
pycine_lite-0.4.0.dist-info/RECORD
