Metadata-Version: 2.4
Name: pycine-lite
Version: 0.4.0
Summary: Handle .cine files created by Vision Research Phantom® cameras
Author-email: Ben Hagen <ben@ottomatic.io>, "Takeshi (Kesh) Ikuma" <tikuma@lsuhsc.edu>
License: LGPL-3.0 License
Project-URL: Repository, https://github.com/tikuma-lsuhsc/pycine-lite
Classifier: Programming Language :: Python :: 3 :: Only
Classifier: License :: OSI Approved :: GNU Lesser General Public License v3 (LGPLv3)
Classifier: Operating System :: OS Independent
Requires-Python: >=3.9
License-File: LICENSE
Requires-Dist: numpy
Dynamic: license-file
